.appveyor.yml
.bumpversion.cfg
.cookiecutterrc
.coveragerc
.editorconfig
.pre-commit-config.yaml
.readthedocs.yml
.travis.yml
AUTHORS.rst
CHANGELOG.rst
CONTRIBUTING.rst
LICENSE
MANIFEST.in
README.rst
setup.cfg
setup.py
tox.ini
ci/appveyor-with-compiler.cmd
ci/bootstrap.py
ci/requirements.txt
ci/templates/.appveyor.yml
ci/templates/.travis.yml
docs/authors.rst
docs/changelog.rst
docs/conf.py
docs/contributing.rst
docs/index.rst
docs/installation.rst
docs/readme.rst
docs/requirements.txt
docs/spelling_wordlist.txt
docs/usage.rst
docs/reference/celltest.rst
docs/reference/index.rst
src/celltest/__init__.py
src/celltest/__main__.py
src/celltest/cells.py
src/celltest/cli.py
src/celltest/funclib.py
src/celltest/utils.py
src/celltest.egg-info/PKG-INFO
src/celltest.egg-info/SOURCES.txt
src/celltest.egg-info/dependency_links.txt
src/celltest.egg-info/entry_points.txt
src/celltest.egg-info/not-zip-safe
src/celltest.egg-info/requires.txt
src/celltest.egg-info/top_level.txt
src/celltest/templates/01_template_default.py
src/celltest/templates/02_template_min.py
tests/cells.ipynb
tests/example.ipynb
tests/header
tests/test_cells.py
tests/test_celltest.py
tests/test_example.py
tests/.ipynb_checkpoints/cells-checkpoint.ipynb
tests/.ipynb_checkpoints/example-checkpoint.ipynb