Metadata-Version: 2.1
Name: celltest
Version: 0.0.2
Summary: Convert notebook cells to unittests
Home-page: https://github.com/NikZak/celltest
Author: Nikolay Zakirov
Author-email: nickzakirov@gmail.com
License: MIT
Project-URL: Documentation, https://celltest.readthedocs.io/
Project-URL: Changelog, https://celltest.readthedocs.io/en/latest/changelog.html
Project-URL: Issue Tracker, https://github.com/NikZak/celltest/issues
Platform: UNKNOWN
Classifier: Development Status :: 5 - Production/Stable
Classifier: Intended Audience :: Developers
Classifier: License :: OSI Approved :: MIT License
Classifier: Operating System :: Unix
Classifier: Operating System :: POSIX
Classifier: Operating System :: Microsoft :: Windows
Classifier: Programming Language :: Python
Classifier: Programming Language :: Python :: 3.7
Classifier: Programming Language :: Python :: 3.8
Classifier: Topic :: Utilities
Requires-Python: >=3.7
Provides-Extra: black
Provides-Extra: isort
Provides-Extra: yapf
